{
    "A02": "6.1.1",
    "A03": "SI",
    "B11": "Poka\u017ei podrobne informacije o surovinah",
    "B17": "Proizvodnja",
    "C41": "Aliansa",
    "C42": "Krilo",
    "C43": "Bootcamp",
    "C44": "Konfederacija",
    "C45": "Trgovec",
    "C46": "Prijatelji",
    "C48": "Sovra\u017enik",
    "C49": "Vojna",
    "C51": "Kolegi",
    "C55": "Trgovec",
    "C61": "Mo\u017een napad",
    "C62": "Opazuj",
    "C63": "Opazuja 2",
    "C64": "Farma",
    "C65": "Farma 2",
    "C66": "Tar\u010da",
    "C67": "Napad",
    "C81": "Trenutno",
    "CA9": "Odstrani skupino",
    "D62": "Neobvezno ime za set varnostnih kopij (4-30 \u010drk)",
    "DT1": "Poka\u017ei podrobnej\u0161e informacije",
    "E18": "R",
    "F05": "Rutinski",
    "F16": "Prilagodi hitrost glede na razpolo\u017eljivo kapaciteto ali koli\u010dino deuteriuma",
    "F18": "Odstrani opozorilo da kolonizacija ni ve\u010d mo\u017ena",
    "F23": "Kapasitesi",
    "F26": "Ekspedicijske to\u010dke",
    "F37": "Izberi najve\u010dje \u0161t. ladij",
    "F38": "Nalo\u017ei najve\u010djo koli\u010dino surovin",
    "F39": "Ponastavi",
    "F40": "Standardne tar\u010de",
    "F65": "Trajanje",
    "F67": "Poraba",
    "F70": "Ekspedicije",
    "F80": "zbiranje",
    "F90": "fleetsave",
    "FL0": "Zadnja misija",
    "G34": "Ostani na trenutni luni po skoku",
    "I0T": "Pripni podrobnosti v plo\u0161\u010do informacij",
    "I60": "Aliansa",
    "K091": "Metal",
    "K092": "Krist.",
    "K093": "Devt.",
    "K202": "MTL",
    "K203": "VTL",
    "K204": "LL",
    "K205": "TL",
    "K206": "Kri\u017e.",
    "K207": "BL",
    "K208": "Kolon.",
    "K209": "Rec.",
    "K210": "Sonda",
    "K211": "Bomb.",
    "K212": "Sat.",
    "K213": "Uni\u010d.",
    "K214": "ZS",
    "K215": "BK",
    "L081": "Planet",
    "L082": "Ru\u0161evine",
    "L083": "Luna",
    "M22": "Ru\u0161evine",
    "M24": "Plen",
    "M28": "Poka\u017ei vale plenjenja",
    "M30": "Skrij poro\u010dila pod mejo ali skrij podrobnosti",
    "M31": "Skrij vse",
    "M32": "Skrij pod mejo, zgradbe, raziskave",
    "M33": "Skrij pod mejo, zgradbe",
    "M34": "Skrij pod mejo",
    "M35": "Prika\u017ei vse",
    "M80": "Izbri\u0161i prikazana ali ozna\u010dena sporo\u010dila z zadevo $subject",
    "M81": "Ozna\u010di prikazana ali izbrana sporo\u010dila kot prebrana",
    "M82": "Izbri\u0161i prikazana ali ozna\u010dena vohunska poro\u010dila s plenom pod $plunder in ru\u0161evinami pod $debris",
    "M83": "Izbri\u0161i prikazana ali ozna\u010dena bojna poro\u010dila z izgubami pod",
    "M84": "Izbri\u0161i prikazana ali ozna\u010dena bojna poro\u010dila na ekspedicijah",
    "M85": "Izbri\u0161i prikazana ali ozna\u010dena sporo\u010dila igralcev",
    "M86": "Vohuni ob",
    "M87": "Povratek flote",
    "M91": "Izbri\u0161i prikazana ali ozne\u010dena sporo\u010dila",
    "X01": "Nastavi simulirane ladje v OGame",
    "X02": "Takti\u010dni umik \/ ladje",
    "X03": "Razmerje ropanja",
    "X04": "Faktor hitrosti"
}